{"note":"This file is an internal implementation detail to speed up HTML report generation. Its format can change at any time. You might be looking for the JSON report: https://coverage.rtfd.io/cmd.html#cmd-json","format":5,"version":"7.13.0","globals":"754438156a9fd37aaf2d7b709da73b83","files":{"z_9be5db1a1db91e15___init___py":{"hash":"c206f645edb085ab25c8c1f713948556","index":{"url":"z_9be5db1a1db91e15___init___py.html","file":"src/profiler_cub/_internal/__init__.py","description":"","nums":{"precision":2,"n_files":1,"n_statements":0,"n_excluded":0,"n_missing":0,"n_branches":0,"n_partial_branches":0,"n_missing_branches":0}}},"z_9be5db1a1db91e15__cmds_py":{"hash":"646542656f88ed789dd6371f1e9ab99d","index":{"url":"z_9be5db1a1db91e15__cmds_py.html","file":"src/profiler_cub/_internal/_cmds.py","description":"","nums":{"precision":2,"n_files":1,"n_statements":25,"n_excluded":0,"n_missing":25,"n_branches":0,"n_partial_branches":0,"n_missing_branches":0}}},"z_9be5db1a1db91e15__exit_code_py":{"hash":"a318397eacdaa8b428dcaf7854752533","index":{"url":"z_9be5db1a1db91e15__exit_code_py.html","file":"src/profiler_cub/_internal/_exit_code.py","description":"","nums":{"precision":2,"n_files":1,"n_statements":24,"n_excluded":0,"n_missing":24,"n_branches":0,"n_partial_branches":0,"n_missing_branches":0}}},"z_9be5db1a1db91e15__info_py":{"hash":"300b2c02b2cc40e6441f93dcfbc9c486","index":{"url":"z_9be5db1a1db91e15__info_py.html","file":"src/profiler_cub/_internal/_info.py","description":"","nums":{"precision":2,"n_files":1,"n_statements":64,"n_excluded":0,"n_missing":22,"n_branches":0,"n_partial_branches":0,"n_missing_branches":0}}},"z_9be5db1a1db91e15__version_py":{"hash":"6bed365caf0da0c13804514a59696d65","index":{"url":"z_9be5db1a1db91e15__version_py.html","file":"src/profiler_cub/_internal/_version.py","description":"","nums":{"precision":2,"n_files":1,"n_statements":3,"n_excluded":0,"n_missing":0,"n_branches":0,"n_partial_branches":0,"n_missing_branches":0}}},"z_9be5db1a1db91e15__versioning_py":{"hash":"7f163432998e78b3b52fc12f47502f42","index":{"url":"z_9be5db1a1db91e15__versioning_py.html","file":"src/profiler_cub/_internal/_versioning.py","description":"","nums":{"precision":2,"n_files":1,"n_statements":6,"n_excluded":74,"n_missing":6,"n_branches":0,"n_partial_branches":0,"n_missing_branches":0}}},"z_9be5db1a1db91e15_cli_py":{"hash":"e8a7387a817a627694e6e0e5e349f350","index":{"url":"z_9be5db1a1db91e15_cli_py.html","file":"src/profiler_cub/_internal/cli.py","description":"","nums":{"precision":2,"n_files":1,"n_statements":23,"n_excluded":2,"n_missing":18,"n_branches":10,"n_partial_branches":1,"n_missing_branches":9}}},"z_9be5db1a1db91e15_debug_py":{"hash":"a62bfd76fbb78e2803a282ebc15ddd2f","index":{"url":"z_9be5db1a1db91e15_debug_py.html","file":"src/profiler_cub/_internal/debug.py","description":"","nums":{"precision":2,"n_files":1,"n_statements":59,"n_excluded":0,"n_missing":59,"n_branches":16,"n_partial_branches":0,"n_missing_branches":16}}},"z_7a229b49162c6dd8__stats_py":{"hash":"dbfda68cab62dea8a10c3fb3776b9ffa","index":{"url":"z_7a229b49162c6dd8__stats_py.html","file":"src/profiler_cub/_stats.py","description":"","nums":{"precision":2,"n_files":1,"n_statements":3,"n_excluded":8,"n_missing":0,"n_branches":0,"n_partial_branches":0,"n_missing_branches":0}}},"z_7a229b49162c6dd8_common_py":{"hash":"d347e64b60a7bb87d305d02074bc5889","index":{"url":"z_7a229b49162c6dd8_common_py.html","file":"src/profiler_cub/common.py","description":"","nums":{"precision":2,"n_files":1,"n_statements":72,"n_excluded":4,"n_missing":31,"n_branches":12,"n_partial_branches":0,"n_missing_branches":12}}},"z_7a229b49162c6dd8_core_py":{"hash":"84b96d484f6871720c0b0d10815d83ba","index":{"url":"z_7a229b49162c6dd8_core_py.html","file":"src/profiler_cub/core.py","description":"","nums":{"precision":2,"n_files":1,"n_statements":150,"n_excluded":4,"n_missing":128,"n_branches":54,"n_partial_branches":0,"n_missing_branches":54}}},"z_7a229b49162c6dd8_display_py":{"hash":"1dca9c51c18a464eab85b0eabbcb6add","index":{"url":"z_7a229b49162c6dd8_display_py.html","file":"src/profiler_cub/display.py","description":"","nums":{"precision":2,"n_files":1,"n_statements":166,"n_excluded":11,"n_missing":140,"n_branches":48,"n_partial_branches":0,"n_missing_branches":48}}},"z_7a229b49162c6dd8_models_py":{"hash":"85482604a916f87376fb4552cf23301b","index":{"url":"z_7a229b49162c6dd8_models_py.html","file":"src/profiler_cub/models.py","description":"","nums":{"precision":2,"n_files":1,"n_statements":68,"n_excluded":0,"n_missing":10,"n_branches":2,"n_partial_branches":0,"n_missing_branches":2}}},"z_7a229b49162c6dd8_api_py":{"hash":"f90cf2dfb89f731fc5eed4a874f00c57","index":{"url":"z_7a229b49162c6dd8_api_py.html","file":"src/profiler_cub/api.py","description":"","nums":{"precision":2,"n_files":1,"n_statements":127,"n_excluded":5,"n_missing":105,"n_branches":20,"n_partial_branches":0,"n_missing_branches":20}}}}}