{"data_mtime":1727194602,"dep_lines":[5,6,19,15,16,1,2,1,1,1,1,1,1,1,1,1,1,1,8,9],"dep_prios":[5,5,25,5,5,10,5,5,30,30,30,30,30,30,30,30,30,30,5,5],"dependencies":["invoke.vendor.lexicon","invoke.vendor.fluidity","invoke.parser.context","invoke.exceptions","invoke.util","copy","typing","builtins","_typeshed","abc","importlib","importlib.machinery","invoke.parser.argument","invoke.vendor","invoke.vendor.fluidity.machine","invoke.vendor.lexicon.alias_dict","invoke.vendor.lexicon.attribute_dict","logging"],"hash":"83df4d720cc719f123b0dcf0c85980a3f31186a9467fcd925d70733995ebe91c","id":"invoke.parser.parser","ignore_all":true,"interface_hash":"9348d93e03ccb42857c4d0db528f932a60a5b965787cbaf8f30dede8a69634ff","mtime":1689185096,"options":{"allow_redefinition":false,"allow_untyped_globals":false,"always_false":[],"always_true":[],"bazel":false,"check_untyped_defs":false,"disable_bytearray_promotion":false,"disable_error_code":[],"disable_memoryview_promotion":false,"disabled_error_codes":[],"disallow_any_decorated":false,"disallow_any_explicit":false,"disallow_any_expr":false,"disallow_any_generics":false,"disallow_any_unimported":false,"disallow_incomplete_defs":false,"disallow_subclassing_any":false,"disallow_untyped_calls":false,"disallow_untyped_decorators":false,"disallow_untyped_defs":false,"enable_error_code":[],"enabled_error_codes":[],"extra_checks":false,"follow_imports":"normal","follow_imports_for_stubs":false,"ignore_errors":false,"ignore_missing_imports":false,"implicit_optional":false,"implicit_reexport":true,"local_partial_types":false,"mypyc":false,"old_type_inference":false,"platform":"linux","plugins":[],"strict_concatenate":false,"strict_equality":false,"strict_optional":true,"warn_no_return":true,"warn_return_any":false,"warn_unreachable":false,"warn_unused_ignores":false},"path":"/usr/lib/python3/dist-packages/invoke/parser/parser.py","plugin_data":null,"size":19809,"suppressed":["lexicon","fluidity"],"version_id":"1.11.2"}