{
    "font_title": "LXGW",
    "font_size_title": "large",
    "font_weight_title": "bold",
    "font_content": "LXGW",
    "font_size_content": "medium",
    "font_weight_content": "normal",
    "font_marker": "LXGW",
    "font_size_marker": "small",
    "font_weight_marker": "normal",
    "color_palette": [
        "#14517C",
        "#2F7FC1",
        "#E7EFFA",
        "#96C37D",
        "#F3D266",
        "#F7E1ED",
        "#F8F3F9",
        "#C497B2",
        "#A9B8C6"
    ],
    "color_highlight": [
        "#D8383A",
        "#541617"
    ]
}