[{"C": "/* vim: set ts={ts} sts={sts} sw={sw} {et} ai si sta: */", "H": "/* vim: set ts={ts} sts={sts} sw={sw} {et} ai si sta: */", "Makefile": "# vim: set ts={ts} sts={sts} sw={sw} {et} ai si sta:", "bash": "# vim: set ts={ts} sts={sts} sw={sw} {et} ai si sta:", "c": "/* vim: set ts={ts} sts={sts} sw={sw} {et} ai si sta: */", "cc": "/* vim: set ts={ts} sts={sts} sw={sw} {et} ai si sta: */", "cpp": "/* vim: set ts={ts} sts={sts} sw={sw} {et} ai si sta: */", "css": "/* vim: set ts={ts} sts={sts} sw={sw} {et} ai si sta: */", "fish": "# vim: set ts={ts} sts={sts} sw={sw} {et} ai si sta:", "h": "/* vim: set ts={ts} sts={sts} sw={sw} {et} ai si sta: */", "hh": "/* vim: set ts={ts} sts={sts} sw={sw} {et} ai si sta: */", "hpp": "/* vim: set ts={ts} sts={sts} sw={sw} {et} ai si sta: */", "htm": "<!-- vim: set ts={ts} sts={sts} sw={sw} {et} ai si sta: -->", "html": "<!-- vim: set ts={ts} sts={sts} sw={sw} {et} ai si sta: -->", "latex": "% vim: set ts={ts} sts={sts} sw={sw} {et} ai si sta:", "lua": "-- vim: set ts={ts} sts={sts} sw={sw} {et} ai si sta:", "markdown": "<!-- vim: set ts={ts} sts={sts} sw={sw} {et} ai si sta: -->", "md": "<!-- vim: set ts={ts} sts={sts} sw={sw} {et} ai si sta: -->", "mk": "# vim: set ts={ts} sts={sts} sw={sw} {et} ai si sta:", "py": "# vim: set ts={ts} sts={sts} sw={sw} {et} ai si sta:", "pyi": "# vim: set ts={ts} sts={sts} sw={sw} {et} ai si sta:", "rb": "# vim: set ts={ts} sts={sts} sw={sw} {et} ai si sta:", "sh": "# vim: set ts={ts} sts={sts} sw={sw} {et} ai si sta:", "tex": "% vim: set ts={ts} sts={sts} sw={sw} {et} ai si sta:", "xml": "<!-- vim: set ts={ts} sts={sts} sw={sw} {et} ai si sta: -->", "zsh": "# vim: set ts={ts} sts={sts} sw={sw} {et} ai si sta:"}, {"C": {"level": 2, "expandtab": true}, "H": {"level": 2, "expandtab": true}, "Makefile": {"level": 4, "expandtab": false}, "bash": {"level": 4, "expandtab": true}, "c": {"level": 2, "expandtab": true}, "cc": {"level": 2, "expandtab": true}, "cpp": {"level": 2, "expandtab": true}, "css": {"level": 4, "expandtab": true}, "fish": {"level": 4, "expandtab": true}, "h": {"level": 2, "expandtab": true}, "hh": {"level": 2, "expandtab": true}, "hpp": {"level": 2, "expandtab": true}, "htm": {"level": 2, "expandtab": true}, "html": {"level": 2, "expandtab": true}, "latex": {"level": 2, "expandtab": true}, "lua": {"level": 4, "expandtab": true}, "markdown": {"level": 2, "expandtab": true}, "md": {"level": 2, "expandtab": true}, "mk": {"level": 4, "expandtab": false}, "py": {"level": 4, "expandtab": true}, "pyi": {"level": 4, "expandtab": true}, "rb": {"level": 4, "expandtab": true}, "sh": {"level": 4, "expandtab": true}, "tex": {"level": 2, "expandtab": true}, "xml": {"level": 2, "expandtab": true}, "zsh": {"level": 4, "expandtab": true}}]
