{
  "presentation_title": "Be Fruitful and Multiply",
  "presentation_subtitle": "In Every area - பலுகிப் பெருகுங்கள் - எல்லாவற்றிலும்",
  "sections": [
    {
      "section": "Be Fruitful and Multiply",
      "verses": [
        {
          "reference": "மத்தேயு 9:20-22 (TAOVBSI)",
          "text": "அப்பொழுது, பன்னிரண்டு வருஷமாய்ப் பெரும்பாடுற்ற ஒரு ஸ்திரீ: \"நான் அவருடைய வஸ்திரத்தையாவது தொட்டால், நான் சொஸ்தமாவேன்\" என்று தன் உள்ளத்தில் நினைத்து, அவர் பின்னாலிருந்து வந்து, அவர் உடையின் ஓரத்தைத் தொட்டாள்."
        },
        {
          "reference": "ஆழமாக யோசிக்கவும்",
          "text": ""
        },
        {
          "reference": "மத்தேயு 9:22 (TAOVBSI)",
          "text": "இயேசு திரும்பி, அவளைப் பார்த்து: \"மகளே, திடன்கொள்; உன் விசுவாசம் உனக்கு குணமளித்தது\" என்றார். உடனேயே அந்த ஸ்திரீ நிறைந்த குணமடைந்தாள்."
        },
        {
          "reference": "நீ இயேசுவைத் தொட்டால், உனக்கு குணமாவா?",
          "text": ""
        },
        {
          "reference": "லூக்கா 8:45 (TAOVBSI)",
          "text": "அப்பொழுது இயேசு: \"என்னைத் தொட்டது யார்?\" என்று கேட்டார். எவருக்கும் தெரியாமல் כולם மறுத்துவிட்ட போது, பேதுருவும் அவனுடன் இருந்தவர்கள் கூறினார்கள்: \"ஆண்டவரே, திரளான மக்கள் உம்மைச் சூழ்ந்து நெருக்கிக்கொண்டு இருக்கிறார்களே; இன்னும் 'என்னைத் தொட்டது யார்?' என்று கேட்கிறீர்களா!\""
        },
        {
          "reference": "இந்த உலகத்திற்கு ஒப்பாகாதிருங்கள்",
          "text": ""
        },
        {
          "reference": "ரோமர் 12:2 (TAOVBSI)",
          "text": "நீங்கள் இந்தப் பிரபஞ்சத்துக்கு ஒத்திருக்கும் முறையை மேற்கொள்ளாமல், உங்கள் மனம் புதிதாக மாற்றப்படுவதால் மறுரூபமடைந்தவர்களாய் இருங்கள்; அப்பொழுது தேவனுடைய நன்மையும் பிரியமும் பூரணமுமான சித்தம் என்பதென்ன என்பது உங்கள் அறிவுக்கு புரியும்."
        },
        {
          "reference": "ரோமர் 12:2 (மற்றொரு வடிவம்)",
          "text": "நீங்கள் இந்தப் பிரபஞ்சத்துக்கு ஒத்த வேஷம் ஏட்காதீர்கள்; ஆனால, உங்கள் மனத்தை புதிதாக்குவதால் மாற்றமடைவதால் மாறுபடுங்கள். அப்பொழுது தேவனுடைய நன்மையான, உற்றபிரியமான, சாக்ரபூரணமான சித்தம் என்ன என நீங்கள் விவேசித்து அறியக்கூடியவர்களாக இருப்பீர்கள்."
        },
        {
          "reference": "எபிரெயர் 11:1 (TAOVBSI)",
          "text": "விசுவாசம் என்பது நம்பப்பட்ட காரியங்களின் உறுதியும், காணப்படாதவற்றின் நிச்சயமுமாகும்."
        },
        {
          "reference": "மத்தேயு 9:20-21 (TAOVBSI மற்றொரு வடிவம்)",
          "text": "அப்பொழுது, பன்னிரண்டு வருஷமாய்ப் பெரும்பாடுற்ற ஒரு ஸ்திரீ: \"நான் அவருடைய ஆடையின்கூட தொட்டாலுமே, நான் குணமடைவேன்\" என்று மனதில் எண்ணி, பின்னால் வந்து, அவருடைய ஆடையின் அசைவைக் கொண்டாள்."
        },
        {
          "reference": "யோவான் 16:33 (TAOVBSI)",
          "text": "\"இவற்றைப் பற்றிப் நான் உங்களோடு பேசித் கூறியுள்ளேன், எனதருகில் உங்களுக்குச் சமாதானம் உண்டாகும்படி. உலகத்தில் உங்களுக்கு துன்பம் உண்டு; ஆனாலும் திடன்கொள்ளுங்கள்; நான் உலகத்தை வென்றேன்.\""
        },
        {
          "reference": "யோவான் 16:33 (மற்றொரு வடிவம்)",
          "text": "\"நான் இவை அனைத்தையும் உங்களுக்குச் சொல்லியதன் நோக்கம், என்னிலேயே உங்களுக்குச் சமாதானம் கிடைக்குமென்றது. உலகத்தில் உங்களுக்கு துன்பம் உண்டு. ஆனால் தெவிட்டாதிருங்கள்; நான் உலகத்தை ஜெயித்தேன்.\""
        },
        {
          "reference": "1 யோவான் 5:4 (TAOVBSI)",
          "text": "தேவனினால் பிறப்பதெல்லாம் உலகத்தை ஜெயிக்கும்; நம்முடைய விசுவாசமே உலகத்தை ஜெயிக்கும் ஜெயம் ஆகும்."
        },
        {
          "reference": "சங்கீதம் 109:17 (TAOVBSI)",
          "text": "சாபத்தை விரும்பினான்; அது அவனுக்கு வந்தது. அவன் ஆசீர்வாதத்தை விரும்பவில்லை; அது அவனைவிட்டு தூரமாய்ப் போயிற்று."
        },
        {
          "reference": "ஆதியாகமம் 13:15 (TAOVBSI)",
          "text": "நீ காண்கிற இந்த நிலமெங்கும், அதை உனக்கும் உன் சந்ததிக்கும் என்றென்றைக்கும் கொடுப்பேன்."
        },
        {
          "reference": "யோசுவா 1:3 (TAOVBSI)",
          "text": "நான் மோசேயிடம் சொல்லியபடி, நீங்கள் காலை வைத்த நிலமெல்லாம் உங்களுக்கு அளிக்கப்பட்டிருக்கிறது."
        },
        {
          "reference": "எபிரெயர் 11:1 (மற்றொரு வடிவம்)",
          "text": "விசுவாசம் என்பது நம்பியுள்ளவைகளின் உறுதியும், காணப்படாதவைகளின் பிரமாணமுமாகும்."
        }
      ]
    },
    {
      "section": "நாம் பாவிகள் என்பதை உணருதல்",
      "verses": [
        {
          "reference": "லேவியராகமம் 15:19 (TAOVBSI)",
          "text": "சூதகஸ்திரீ தன் சரீரத்திலிருந்து இரத்தஊறினால், ஏழு நாட்கள் தனி பிரிவில் இருக்க வேண்டும்; அவளைத் தொடும் யாவரும் அன்றைய மாலை வரை அக்வுடனாக இருப்பார்கள்."
        },
        {
          "reference": "லூக்கா 18:10-12 (TAOVBSI)",
          "text": "\"இரு اشخাص ஜெபிக்க கோவிலுக்குச் சென்றனர்; ஒருவர் பரிசேயரும் மற்றவர் வரி வசூலிப்பவரும். பரிசேயர் நின்று ஜெபித்து: 'தேவனே, நான் மற்ற மனிதர்களைப் போல கொள்ளையர், அநியாயக்காரர், விபசாரி அல்ல, இதோ இந்த வரி வசூலிபவனைக் கூட அல்ல என்பதற்காக உமக்கு நன்றி செலுத்துகிறேன். நான் வாரத்தில் இரண்டு முறை நோன்பிருந்து, என்னைப் பொருந்திய அனைத்திலும் பத்தீத்வீதம் செலுத்துகின்றேன்.'\""
        },
        {
          "reference": "லூக்கா 18:13-14 (TAOVBSI)",
          "text": "\"ஆயாக்காரன் தூரத்தில் நின்று, விண்ணைப் நோக்கிட அஞ்சியவனாய் தன் மார்பைத் தட்டிக்கொண்டு: 'தேவனே, பாவியான எனக்கு இரங்கும்' என்று ஜெபித்தான். நான் உங்களுக்குச் சொல்கிறேன்: பாவியாய் ஜெபித்த இந்த மனிதனே நீதிமானாக்கப்பட்டவனாய், மறுபடியும் தன் இல்லத்துக்குத் திரும்பினான். ஏனென்றால் தன்னை உயர்த்துகிறவன் ஒவ்வொருவரும் தாழ்த்தப்படுவார்; தன்னைத் தாழ்த்துகிறவன் உயர்த்தப்படுவார்.\""
        },
        {
          "reference": "லூக்கா 15:1 (TAOVBSI)",
          "text": "அந்த காலத்தில் அனைத்து வரித்தொழிலாளரும் பாவிகளுமாகியோர், இயேசுவின் வார்த்தைகளை கேட்க அவரை நெருங்கி வந்தார்கள்."
        },
        {
          "reference": "லூக்கா 14:25-27 (TAOVBSI)",
          "text": "அப்போது பேராண்மையான திரளான மக்கள் இயேசுவுடன் பயணம் செய்து கொண்டிருந்தனர். இயேசு அவர்களை நோக்கி திரும்பிச் சொன்னார்: \"யாரென் கிட்ட வருவானும், தன் தந்தையும் தாயும் மனைவியும் பிள்ளைகளும் சகோதரனும் சகோதரியும் கூட, இப்பொழுது தன் உயிரையும் வாரா விரும்பி விலக்கிச் செய்யாவிட்டால், அவன் எனக்கு சீடனாக இருக்க முடியாது. தன் சிலுவையைத் தோளிலே சுமந்துகொண்டு என் பின்னால் வராதவன், எனக்கு சீடராக முடியாது.\""
        },
        {
          "reference": "மத்தேயு 9:12 (TAOVBSI)",
          "text": "ஏசு அதை கேட்டவுடன்: \"பிணியாளர்களுக்கே வைத்தியர் தேவையார்; ஆரோக்கியமுள்ளவர்களுக்கு தேவையில்லை\" என்றார்."
        },
        {
          "reference": "மத்தேயு 9:13 (TAOVBSI)",
          "text": "\"நீதிமான்களை அல்ல, பாவிகளை நான் மனந்திருமிப்பதற்காக அழைத்திருக்கிறேன்\" என்றார்."
        }
      ]
    },
    {
      "section": "அவருடைய நீதி",
      "verses": [
        {
          "reference": "மத்தேயு 9:20-21 (TAOVBSI)",
          "text": "அப்பொழுது, பன்னிரண்டு ஆண்டுகள் இரத்தஊறால் பீடிக்கப் பட்டிருந்த ஒரு பெண், யேசுவின் பின்னால் வந்து அவரது ஆடையின் ஞானியைத் தொட்டாள். அவள் மனதிற்குள்: \"அவருடைய ஆடையின்கூடத் தொட்டாலும்கூட, நானும் குணமடைவேன்\" என்று எண்ணிக்கொண்டாள்."
        },
        {
          "reference": "ஏசாயா 61:10 (TAOVBSI)",
          "text": "அவர் எனக்கு இரட்சிப்பின் வஸ்திரங்களை அணிவித்துப் போர்த்தி, நீதியின் ஆடையையும் எனக்குத் தரித்தார்."
        },
        {
          "reference": "அவள் நோயுற்றதற்குக் காரணம்",
          "text": ""
        },
        {
          "reference": "ஏசாயா 64:6 (TAOVBSI)",
          "text": "நாங்கள் எல்லாரும் அசுத்தமானவர்களாகிவிட்டோம்; எங்கள் நீதிநெறிகள் அனைத்தும் ஒன்றுகூடி அழுக்கான துணியெனக் காணப்படுகிறது."
        },
        {
          "reference": "லூக்கா 8:55 (TAOVBSI)",
          "text": "அப்பொழுது அவளுடைய ஆவி அவளுள் திரும்பிவந்தது; உடனே அவள் எழுந்தாள். இயேசு, \"அவளுக்கு சாப்பிடக் கொடுக்குங்கள்\" என்று கட்டளையிட்டார்."
        },
        {
          "reference": "ஏசாயா 54:17 (TAOVBSI)",
          "text": "உன் விரோதமாக உண்டாக்கப்படும் எந்த ஆயுதமும் வெற்றியடையாது; நியாயத் தீர்ப்பில் உனை எதிர்த்து எழும் நாவெல்லாம் நீ குற்றம்சாட்டுவாய். இதுவே கர்த்தருடையdienரின் சுதந்தரமும், என்னாலேயே உண்டான அவர்களின் நீதியுமாகும் என்று கர்த்தர் உரைக்கிறார்."
        },
        {
          "reference": "எரெமியா 23:4 (TAOVBSI)",
          "text": "நான் அவைகளுக்காக மேய்ப்பர்களை உத்தரவு செய்வேன்; இனி அவை பயப்படமாட்டார்கள், கலங்கமாட்டார்கள், எந்ததொரு மேஷமும் காணாமல் போகமாட்டாது,\" என்று கர்த்தர் சொல்லுகிறார்."
        },
        {
          "reference": "எரெமியா 23:6 (TAOVBSI)",
          "text": "அவரது நாட்களில் யூதா இரட்சிக்கப்படும்; இஸ்ரவேலும் சுகமாய் வாழும். அவருக்கு வழங்கப்படவுள்ள பெயர்: \"எங்கள் நீதியாயிருக்கிற கர்த்தர்\" என்பது."
        }
      ]
    }
  ]
}
