{
  "nodes": [
    {
      "id": "node_0",
      "label": "GET /api/users",
      "title": "GET /api/users\nFile: routes/users.py\nLine: 42\nConnections: 5",
      "method": "GET",
      "path": "/api/users",
      "file": "routes/users.py",
      "line": 42,
      "value": 30,
      "size": 30,
      "color": {
        "background": "#7c3aed",
        "border": "#7c3aed",
        "highlight": {
          "background": "#7c3aed",
          "border": "#ffffff"
        }
      },
      "font": {
        "color": "#ffffff",
        "size": 14,
        "face": "JetBrains Mono"
      },
      "borderWidth": 2,
      "connections": 5,
      "high_impact": false
    },
    {
      "id": "node_1",
      "label": "UNKNOWN /api/unknown",
      "title": "UNKNOWN /api/unknown\nFile: unknown\nLine: ?\nConnections: 1",
      "method": "UNKNOWN",
      "path": "/api/unknown",
      "file": "unknown",
      "line": "?",
      "value": 18,
      "size": 18,
      "color": {
        "background": "#666666",
        "border": "#666666",
        "highlight": {
          "background": "#666666",
          "border": "#ffffff"
        }
      },
      "font": {
        "color": "#ffffff",
        "size": 14,
        "face": "JetBrains Mono"
      },
      "borderWidth": 2,
      "connections": 1,
      "high_impact": false
    },
    {
      "id": "node_2",
      "label": "POST /api/users",
      "title": "POST /api/users\nFile: routes/users.py\nLine: 58\nConnections: 3",
      "method": "POST",
      "path": "/api/users",
      "file": "routes/users.py",
      "line": 58,
      "value": 24,
      "size": 24,
      "color": {
        "background": "#00ff41",
        "border": "#00ff41",
        "highlight": {
          "background": "#00ff41",
          "border": "#ffffff"
        }
      },
      "font": {
        "color": "#ffffff",
        "size": 14,
        "face": "JetBrains Mono"
      },
      "borderWidth": 2,
      "connections": 3,
      "high_impact": false
    }
  ],
  "edges": [
    {
      "from": "node_0",
      "to": "node_1",
      "label": "UNKNOWN",
      "arrows": "to",
      "color": {
        "color": "#666666",
        "opacity": 0.4
      },
      "width": 1,
      "smooth": {
        "type": "continuous",
        "roundness": 0.5
      }
    },
    {
      "from": "node_0",
      "to": "node_2",
      "label": "POST",
      "arrows": "to",
      "color": {
        "color": "#7c3aed",
        "opacity": 0.6
      },
      "width": 2,
      "smooth": {
        "type": "continuous",
        "roundness": 0.5
      }
    }
  ],
  "summary": {
    "total_nodes": 3,
    "total_edges": 2,
    "endpoints": 3,
    "high_impact": 0,
    "project_name": "Example Project"
  }
}














